{
  "id": 486,
  "name": "regigigas",
  "displayName": "Regigigas",
  "species": {
    "id": 486,
    "name": "regigigas"
  },
  "generation": "generation-iv",
  "types": [
    "normal"
  ],
  "height": 37,
  "weight": 4200,
  "baseExperience": 302,
  "isDefault": true,
  "stats": {
    "hp": 110,
    "attack": 160,
    "defense": 110,
    "specialAttack": 80,
    "specialDefense": 110,
    "speed": 100,
    "total": 670,
    "effort": {
      "attack": 3
    }
  },
  "abilities": [
    {
      "id": 112,
      "name": "slow-start",
      "displayName": "Slow Start",
      "slot": 1,
      "isHidden": false,
      "shortEffect": "Halves Attack and Speed for five turns upon entering battle.",
      "effect": "This Pokémon's Attack and Speed are halved for five turns upon entering battle. This ability also takes effect when acquired during battle. If this Pokémon loses its ability before the five turns are up, its Attack and Speed return to normal; if it then regains this ability without leaving battle, its Attack and Speed are halved again, but the counter keeps counting from where it was.",
      "flavorText": "For five turns, the Pokémon's Attack and Speed stats are halved."
    }
  ],
  "evolution": {
    "file": "../evolutions/regigigas.json",
    "names": [
      "regigigas"
    ]
  },
  "forms": [
    {
      "id": 486,
      "name": "regigigas",
      "displayName": "Regigigas",
      "formName": "regigigas",
      "isDefault": true,
      "isMega": false,
      "isBattleOnly": false,
      "types": [
        "normal"
      ],
      "images": [
        {
          "kind": "front",
          "path": "data/images/486-regigigas/003-endpoints.pokemon.sprites.front_default-486.png",
          "url": "https://raw.githubusercontent.com/PokeAPI/sprites/master/sprites/pokemon/486.png",
          "jsonPath": "endpoints.pokemon.sprites.front_default"
        },
        {
          "kind": "frontShiny",
          "path": "data/images/486-regigigas/004-endpoints.pokemon.sprites.front_shiny-486.png",
          "url": "https://raw.githubusercontent.com/PokeAPI/sprites/master/sprites/pokemon/shiny/486.png",
          "jsonPath": "endpoints.pokemon.sprites.front_shiny"
        },
        {
          "kind": "home",
          "path": "data/images/486-regigigas/006-endpoints.pokemon.sprites.other.home.front_default-486.png",
          "url": "https://raw.githubusercontent.com/PokeAPI/sprites/master/sprites/pokemon/other/home/486.png",
          "jsonPath": "endpoints.pokemon.sprites.other.home.front_default"
        },
        {
          "kind": "home",
          "path": "data/images/486-regigigas/007-endpoints.pokemon.sprites.other.home.front_shiny-486.png",
          "url": "https://raw.githubusercontent.com/PokeAPI/sprites/master/sprites/pokemon/other/home/shiny/486.png",
          "jsonPath": "endpoints.pokemon.sprites.other.home.front_shiny"
        },
        {
          "kind": "back",
          "path": "data/images/486-regigigas/001-endpoints.pokemon.sprites.back_default-486.png",
          "url": "https://raw.githubusercontent.com/PokeAPI/sprites/master/sprites/pokemon/back/486.png",
          "jsonPath": "endpoints.pokemon.sprites.back_default"
        },
        {
          "kind": "dreamWorld",
          "path": "data/images/486-regigigas/005-endpoints.pokemon.sprites.other.dream_world.front_default-486.svg",
          "url": "https://raw.githubusercontent.com/PokeAPI/sprites/master/sprites/pokemon/other/dream-world/486.svg",
          "jsonPath": "endpoints.pokemon.sprites.other.dream_world.front_default"
        },
        {
          "kind": "backShiny",
          "path": "data/images/486-regigigas/002-endpoints.pokemon.sprites.back_shiny-486.png",
          "url": "https://raw.githubusercontent.com/PokeAPI/sprites/master/sprites/pokemon/back/shiny/486.png",
          "jsonPath": "endpoints.pokemon.sprites.back_shiny"
        },
        {
          "kind": "officialArtwork",
          "path": "data/images/486-regigigas/008-endpoints.pokemon.sprites.other.official-artwork.front_default-486.png",
          "url": "https://raw.githubusercontent.com/PokeAPI/sprites/master/sprites/pokemon/other/official-artwork/486.png",
          "jsonPath": "endpoints.pokemon.sprites.other.official-artwork.front_default"
        },
        {
          "kind": "showdown",
          "path": "data/images/486-regigigas/010-endpoints.pokemon.sprites.other.showdown.back_default-486.gif",
          "url": "https://raw.githubusercontent.com/PokeAPI/sprites/master/sprites/pokemon/other/showdown/back/486.gif",
          "jsonPath": "endpoints.pokemon.sprites.other.showdown.back_default"
        },
        {
          "kind": "showdown",
          "path": "data/images/486-regigigas/011-endpoints.pokemon.sprites.other.showdown.back_shiny-486.gif",
          "url": "https://raw.githubusercontent.com/PokeAPI/sprites/master/sprites/pokemon/other/showdown/back/shiny/486.gif",
          "jsonPath": "endpoints.pokemon.sprites.other.showdown.back_shiny"
        },
        {
          "kind": "officialArtworkShiny",
          "path": "data/images/486-regigigas/009-endpoints.pokemon.sprites.other.official-artwork.front_shiny-486.png",
          "url": "https://raw.githubusercontent.com/PokeAPI/sprites/master/sprites/pokemon/other/official-artwork/shiny/486.png",
          "jsonPath": "endpoints.pokemon.sprites.other.official-artwork.front_shiny"
        },
        {
          "kind": "showdown",
          "path": "data/images/486-regigigas/013-endpoints.pokemon.sprites.other.showdown.front_shiny-486.gif",
          "url": "https://raw.githubusercontent.com/PokeAPI/sprites/master/sprites/pokemon/other/showdown/shiny/486.gif",
          "jsonPath": "endpoints.pokemon.sprites.other.showdown.front_shiny"
        },
        {
          "kind": "back",
          "path": "data/images/486-regigigas/014-endpoints.pokemon.sprites.versions.generation-iv.diamond-pearl.back_default-486.png",
          "url": "https://raw.githubusercontent.com/PokeAPI/sprites/master/sprites/pokemon/versions/generation-iv/diamond-pearl/back/486.png",
          "jsonPath": "endpoints.pokemon.sprites.versions.generation-iv.diamond-pearl.back_default"
        },
        {
          "kind": "showdown",
          "path": "data/images/486-regigigas/012-endpoints.pokemon.sprites.other.showdown.front_default-486.gif",
          "url": "https://raw.githubusercontent.com/PokeAPI/sprites/master/sprites/pokemon/other/showdown/486.gif",
          "jsonPath": "endpoints.pokemon.sprites.other.showdown.front_default"
        },
        {
          "kind": "backShiny",
          "path": "data/images/486-regigigas/015-endpoints.pokemon.sprites.versions.generation-iv.diamond-pearl.back_shiny-486.png",
          "url": "https://raw.githubusercontent.com/PokeAPI/sprites/master/sprites/pokemon/versions/generation-iv/diamond-pearl/back/shiny/486.png",
          "jsonPath": "endpoints.pokemon.sprites.versions.generation-iv.diamond-pearl.back_shiny"
        },
        {
          "kind": "front",
          "path": "data/images/486-regigigas/016-endpoints.pokemon.sprites.versions.generation-iv.diamond-pearl.front_default-486.png",
          "url": "https://raw.githubusercontent.com/PokeAPI/sprites/master/sprites/pokemon/versions/generation-iv/diamond-pearl/486.png",
          "jsonPath": "endpoints.pokemon.sprites.versions.generation-iv.diamond-pearl.front_default"
        },
        {
          "kind": "frontShiny",
          "path": "data/images/486-regigigas/017-endpoints.pokemon.sprites.versions.generation-iv.diamond-pearl.front_shiny-486.png",
          "url": "https://raw.githubusercontent.com/PokeAPI/sprites/master/sprites/pokemon/versions/generation-iv/diamond-pearl/shiny/486.png",
          "jsonPath": "endpoints.pokemon.sprites.versions.generation-iv.diamond-pearl.front_shiny"
        },
        {
          "kind": "backShiny",
          "path": "data/images/486-regigigas/019-endpoints.pokemon.sprites.versions.generation-iv.heartgold-soulsilver.back_shiny-486.png",
          "url": "https://raw.githubusercontent.com/PokeAPI/sprites/master/sprites/pokemon/versions/generation-iv/heartgold-soulsilver/back/shiny/486.png",
          "jsonPath": "endpoints.pokemon.sprites.versions.generation-iv.heartgold-soulsilver.back_shiny"
        },
        {
          "kind": "front",
          "path": "data/images/486-regigigas/020-endpoints.pokemon.sprites.versions.generation-iv.heartgold-soulsilver.front_default-486.png",
          "url": "https://raw.githubusercontent.com/PokeAPI/sprites/master/sprites/pokemon/versions/generation-iv/heartgold-soulsilver/486.png",
          "jsonPath": "endpoints.pokemon.sprites.versions.generation-iv.heartgold-soulsilver.front_default"
        },
        {
          "kind": "back",
          "path": "data/images/486-regigigas/018-endpoints.pokemon.sprites.versions.generation-iv.heartgold-soulsilver.back_default-486.png",
          "url": "https://raw.githubusercontent.com/PokeAPI/sprites/master/sprites/pokemon/versions/generation-iv/heartgold-soulsilver/back/486.png",
          "jsonPath": "endpoints.pokemon.sprites.versions.generation-iv.heartgold-soulsilver.back_default"
        },
        {
          "kind": "frontShiny",
          "path": "data/images/486-regigigas/021-endpoints.pokemon.sprites.versions.generation-iv.heartgold-soulsilver.front_shiny-486.png",
          "url": "https://raw.githubusercontent.com/PokeAPI/sprites/master/sprites/pokemon/versions/generation-iv/heartgold-soulsilver/shiny/486.png",
          "jsonPath": "endpoints.pokemon.sprites.versions.generation-iv.heartgold-soulsilver.front_shiny"
        },
        {
          "kind": "back",
          "path": "data/images/486-regigigas/022-endpoints.pokemon.sprites.versions.generation-iv.platinum.back_default-486.png",
          "url": "https://raw.githubusercontent.com/PokeAPI/sprites/master/sprites/pokemon/versions/generation-iv/platinum/back/486.png",
          "jsonPath": "endpoints.pokemon.sprites.versions.generation-iv.platinum.back_default"
        },
        {
          "kind": "frontShiny",
          "path": "data/images/486-regigigas/025-endpoints.pokemon.sprites.versions.generation-iv.platinum.front_shiny-486.png",
          "url": "https://raw.githubusercontent.com/PokeAPI/sprites/master/sprites/pokemon/versions/generation-iv/platinum/shiny/486.png",
          "jsonPath": "endpoints.pokemon.sprites.versions.generation-iv.platinum.front_shiny"
        },
        {
          "kind": "front",
          "path": "data/images/486-regigigas/024-endpoints.pokemon.sprites.versions.generation-iv.platinum.front_default-486.png",
          "url": "https://raw.githubusercontent.com/PokeAPI/sprites/master/sprites/pokemon/versions/generation-iv/platinum/486.png",
          "jsonPath": "endpoints.pokemon.sprites.versions.generation-iv.platinum.front_default"
        },
        {
          "kind": "backShiny",
          "path": "data/images/486-regigigas/023-endpoints.pokemon.sprites.versions.generation-iv.platinum.back_shiny-486.png",
          "url": "https://raw.githubusercontent.com/PokeAPI/sprites/master/sprites/pokemon/versions/generation-iv/platinum/back/shiny/486.png",
          "jsonPath": "endpoints.pokemon.sprites.versions.generation-iv.platinum.back_shiny"
        },
        {
          "kind": "front",
          "path": "data/images/486-regigigas/026-endpoints.pokemon.sprites.versions.generation-ix.scarlet-violet.front_default-486.png",
          "url": "https://raw.githubusercontent.com/PokeAPI/sprites/master/sprites/pokemon/versions/generation-ix/scarlet-violet/486.png",
          "jsonPath": "endpoints.pokemon.sprites.versions.generation-ix.scarlet-violet.front_default"
        },
        {
          "kind": "back",
          "path": "data/images/486-regigigas/027-endpoints.pokemon.sprites.versions.generation-v.black-white.animated.back_default-486.gif",
          "url": "https://raw.githubusercontent.com/PokeAPI/sprites/master/sprites/pokemon/versions/generation-v/black-white/animated/back/486.gif",
          "jsonPath": "endpoints.pokemon.sprites.versions.generation-v.black-white.animated.back_default"
        },
        {
          "kind": "front",
          "path": "data/images/486-regigigas/029-endpoints.pokemon.sprites.versions.generation-v.black-white.animated.front_default-486.gif",
          "url": "https://raw.githubusercontent.com/PokeAPI/sprites/master/sprites/pokemon/versions/generation-v/black-white/animated/486.gif",
          "jsonPath": "endpoints.pokemon.sprites.versions.generation-v.black-white.animated.front_default"
        },
        {
          "kind": "backShiny",
          "path": "data/images/486-regigigas/028-endpoints.pokemon.sprites.versions.generation-v.black-white.animated.back_shiny-486.gif",
          "url": "https://raw.githubusercontent.com/PokeAPI/sprites/master/sprites/pokemon/versions/generation-v/black-white/animated/back/shiny/486.gif",
          "jsonPath": "endpoints.pokemon.sprites.versions.generation-v.black-white.animated.back_shiny"
        },
        {
          "kind": "frontShiny",
          "path": "data/images/486-regigigas/030-endpoints.pokemon.sprites.versions.generation-v.black-white.animated.front_shiny-486.gif",
          "url": "https://raw.githubusercontent.com/PokeAPI/sprites/master/sprites/pokemon/versions/generation-v/black-white/animated/shiny/486.gif",
          "jsonPath": "endpoints.pokemon.sprites.versions.generation-v.black-white.animated.front_shiny"
        },
        {
          "kind": "back",
          "path": "data/images/486-regigigas/031-endpoints.pokemon.sprites.versions.generation-v.black-white.back_default-486.png",
          "url": "https://raw.githubusercontent.com/PokeAPI/sprites/master/sprites/pokemon/versions/generation-v/black-white/back/486.png",
          "jsonPath": "endpoints.pokemon.sprites.versions.generation-v.black-white.back_default"
        },
        {
          "kind": "front",
          "path": "data/images/486-regigigas/033-endpoints.pokemon.sprites.versions.generation-v.black-white.front_default-486.png",
          "url": "https://raw.githubusercontent.com/PokeAPI/sprites/master/sprites/pokemon/versions/generation-v/black-white/486.png",
          "jsonPath": "endpoints.pokemon.sprites.versions.generation-v.black-white.front_default"
        },
        {
          "kind": "backShiny",
          "path": "data/images/486-regigigas/032-endpoints.pokemon.sprites.versions.generation-v.black-white.back_shiny-486.png",
          "url": "https://raw.githubusercontent.com/PokeAPI/sprites/master/sprites/pokemon/versions/generation-v/black-white/back/shiny/486.png",
          "jsonPath": "endpoints.pokemon.sprites.versions.generation-v.black-white.back_shiny"
        },
        {
          "kind": "frontShiny",
          "path": "data/images/486-regigigas/034-endpoints.pokemon.sprites.versions.generation-v.black-white.front_shiny-486.png",
          "url": "https://raw.githubusercontent.com/PokeAPI/sprites/master/sprites/pokemon/versions/generation-v/black-white/shiny/486.png",
          "jsonPath": "endpoints.pokemon.sprites.versions.generation-v.black-white.front_shiny"
        },
        {
          "kind": "front",
          "path": "data/images/486-regigigas/035-endpoints.pokemon.sprites.versions.generation-vi.omegaruby-alphasapphire.front_default-486.png",
          "url": "https://raw.githubusercontent.com/PokeAPI/sprites/master/sprites/pokemon/versions/generation-vi/omegaruby-alphasapphire/486.png",
          "jsonPath": "endpoints.pokemon.sprites.versions.generation-vi.omegaruby-alphasapphire.front_default"
        },
        {
          "kind": "frontShiny",
          "path": "data/images/486-regigigas/036-endpoints.pokemon.sprites.versions.generation-vi.omegaruby-alphasapphire.front_shiny-486.png",
          "url": "https://raw.githubusercontent.com/PokeAPI/sprites/master/sprites/pokemon/versions/generation-vi/omegaruby-alphasapphire/shiny/486.png",
          "jsonPath": "endpoints.pokemon.sprites.versions.generation-vi.omegaruby-alphasapphire.front_shiny"
        },
        {
          "kind": "front",
          "path": "data/images/486-regigigas/037-endpoints.pokemon.sprites.versions.generation-vi.x-y.front_default-486.png",
          "url": "https://raw.githubusercontent.com/PokeAPI/sprites/master/sprites/pokemon/versions/generation-vi/x-y/486.png",
          "jsonPath": "endpoints.pokemon.sprites.versions.generation-vi.x-y.front_default"
        },
        {
          "kind": "front",
          "path": "data/images/486-regigigas/039-endpoints.pokemon.sprites.versions.generation-vii.icons.front_default-486.png",
          "url": "https://raw.githubusercontent.com/PokeAPI/sprites/master/sprites/pokemon/versions/generation-vii/icons/486.png",
          "jsonPath": "endpoints.pokemon.sprites.versions.generation-vii.icons.front_default"
        },
        {
          "kind": "front",
          "path": "data/images/486-regigigas/040-endpoints.pokemon.sprites.versions.generation-vii.ultra-sun-ultra-moon.front_default-486.png",
          "url": "https://raw.githubusercontent.com/PokeAPI/sprites/master/sprites/pokemon/versions/generation-vii/ultra-sun-ultra-moon/486.png",
          "jsonPath": "endpoints.pokemon.sprites.versions.generation-vii.ultra-sun-ultra-moon.front_default"
        },
        {
          "kind": "frontShiny",
          "path": "data/images/486-regigigas/041-endpoints.pokemon.sprites.versions.generation-vii.ultra-sun-ultra-moon.front_shiny-486.png",
          "url": "https://raw.githubusercontent.com/PokeAPI/sprites/master/sprites/pokemon/versions/generation-vii/ultra-sun-ultra-moon/shiny/486.png",
          "jsonPath": "endpoints.pokemon.sprites.versions.generation-vii.ultra-sun-ultra-moon.front_shiny"
        },
        {
          "kind": "frontShiny",
          "path": "data/images/486-regigigas/038-endpoints.pokemon.sprites.versions.generation-vi.x-y.front_shiny-486.png",
          "url": "https://raw.githubusercontent.com/PokeAPI/sprites/master/sprites/pokemon/versions/generation-vi/x-y/shiny/486.png",
          "jsonPath": "endpoints.pokemon.sprites.versions.generation-vi.x-y.front_shiny"
        },
        {
          "kind": "front",
          "path": "data/images/486-regigigas/043-endpoints.pokemon.sprites.versions.generation-viii.icons.front_default-486.png",
          "url": "https://raw.githubusercontent.com/PokeAPI/sprites/master/sprites/pokemon/versions/generation-viii/icons/486.png",
          "jsonPath": "endpoints.pokemon.sprites.versions.generation-viii.icons.front_default"
        },
        {
          "kind": "front",
          "path": "data/images/486-regigigas/042-endpoints.pokemon.sprites.versions.generation-viii.brilliant-diamond-shining-pearl.front_default-486.png",
          "url": "https://raw.githubusercontent.com/PokeAPI/sprites/master/sprites/pokemon/versions/generation-viii/brilliant-diamond-shining-pearl/486.png",
          "jsonPath": "endpoints.pokemon.sprites.versions.generation-viii.brilliant-diamond-shining-pearl.front_default"
        }
      ],
      "model": {
        "name": "Regigigas",
        "formName": "regular",
        "path": "data/models/486-regigigas/01-regular-Regigigas.glb",
        "url": "https://raw.githubusercontent.com/Pokemon-3D-api/assets/main/models/opt/regular/486.glb"
      }
    }
  ]
}
