{
  "id": 894,
  "name": "regieleki",
  "displayName": "Regieleki",
  "species": {
    "id": 894,
    "name": "regieleki"
  },
  "generation": "generation-viii",
  "types": [
    "electric"
  ],
  "height": 12,
  "weight": 1450,
  "baseExperience": 290,
  "isDefault": true,
  "stats": {
    "hp": 80,
    "attack": 100,
    "defense": 50,
    "specialAttack": 100,
    "specialDefense": 50,
    "speed": 200,
    "total": 580,
    "effort": {
      "speed": 3
    }
  },
  "abilities": [
    {
      "id": 262,
      "name": "transistor",
      "displayName": "Transistor",
      "slot": 1,
      "isHidden": false,
      "shortEffect": "Powers up Electric-type moves.",
      "effect": "Increases the power of Electric-type moves used by this Pokémon by 50%.",
      "flavorText": "Powers up Electric-type moves."
    }
  ],
  "evolution": {
    "file": "../evolutions/regieleki.json",
    "names": [
      "regieleki"
    ]
  },
  "forms": [
    {
      "id": 894,
      "name": "regieleki",
      "displayName": "Regieleki",
      "formName": "regieleki",
      "isDefault": true,
      "isMega": false,
      "isBattleOnly": false,
      "types": [
        "electric"
      ],
      "images": [],
      "model": {
        "name": "Regieleki",
        "formName": "regular",
        "path": "data/models/894-regieleki/01-regular-Regieleki.glb",
        "url": "https://raw.githubusercontent.com/Pokemon-3D-api/assets/main/models/opt/regular/894.glb"
      }
    }
  ]
}
